devpi/__init__.py
devpi/__main__.py
devpi/getjson.py
devpi/hookspecs.py
devpi/index.py
devpi/install.py
devpi/list_remove.py
devpi/login.py
devpi/main.py
devpi/push.py
devpi/pypirc.py
devpi/refresh.py
devpi/test.py
devpi/upload.py
devpi/use.py
devpi/user.py
devpi_client-7.2.0.dist-info/AUTHORS
devpi_client-7.2.0.dist-info/LICENSE
devpi_client-7.2.0.dist-info/METADATA
devpi_client-7.2.0.dist-info/WHEEL
devpi_client-7.2.0.dist-info/entry_points.txt
devpi_client-7.2.0.dist-info/top_level.txt
devpi_client-7.2.0.dist-info/RECORD
