Metadata-Version: 2.1
Name: devpi-client
Version: 7.2.0
Summary: devpi upload/install/... workflow commands for Python developers
Maintainer-email: Florian Schulze <mail@pyfidelity.com>
License: 
Project-URL: Bug Tracker, https://github.com/devpi/devpi/issues
Project-URL: Changelog, https://github.com/devpi/devpi/blob/main/client/CHANGELOG
Project-URL: Documentation, https://doc.devpi.net
Project-URL: Homepage, https://devpi.net
Project-URL: Source Code, https://github.com/devpi/devpi
Classifier: Development Status :: 5 - Production/Stable
Classifier: Environment :: Web Environment
Classifier: Intended Audience :: Developers
Classifier: Intended Audience :: System Administrators
Classifier: License :: OSI Approved :: MIT License
Classifier: Programming Language :: Python :: Implementation :: PyPy
Classifier: Programming Language :: Python :: 3.7
Classifier: Programming Language :: Python :: 3.8
Classifier: Programming Language :: Python :: 3.9
Classifier: Programming Language :: Python :: 3.10
Classifier: Programming Language :: Python :: 3.11
Classifier: Programming Language :: Python :: 3.12
Requires-Python: >=3.7
License-File: LICENSE
License-File: AUTHORS
Requires-Dist: build >=0.7.0
Requires-Dist: check-manifest >=0.28
Requires-Dist: devpi-common <5,>=4dev
Requires-Dist: iniconfig
Requires-Dist: pkginfo >=1.10.0
Requires-Dist: platformdirs
Requires-Dist: pluggy <2.0,>=0.6.0
Requires-Dist: colorama ; platform_system == "Windows"
Requires-Dist: tomli ; python_version < "3.11"
